wikicleaner-0.1.7.dist-info/METADATA
wikicleaner-0.1.7.dist-info/WHEEL
wikicleaner/__init__.py
wikicleaner/wikicleaner.cpython-311-x86_64-linux-gnu.so
wikicleaner-0.1.7.dist-info/RECORD
